solitairenet/__init__.py
solitairenet/_nbdev.py
solitairenet/core.py
solitairenet/game.py
solitairenet-0.0.26.dist-info/LICENSE
solitairenet-0.0.26.dist-info/METADATA
solitairenet-0.0.26.dist-info/WHEEL
solitairenet-0.0.26.dist-info/entry_points.txt
solitairenet-0.0.26.dist-info/top_level.txt
solitairenet-0.0.26.dist-info/RECORD
