Metadata-Version: 2.1
Name: solitairenet
Version: 0.0.26
Summary: Solitaire deep learning library
Home-page: https://github.com/thecharlieblake/solitairenet/tree/master/
Author: thecharlieblake
Author-email: thecharlieblake@gmail.com
License: Apache Software License 2.0
Keywords: solitaire patience deep-learning graph-neural-network gnn
Platform: UNKNOWN
Classifier: Development Status :: 3 - Alpha
Classifier: Intended Audience :: Developers
Classifier: Natural Language :: English
Classifier: Programming Language :: Python :: 3.6
Classifier: Programming Language :: Python :: 3.7
Classifier: Programming Language :: Python :: 3.8
Classifier: License :: OSI Approved :: Apache Software License
Requires-Python: >=3.6
Requires-Dist: numpy
